filecrusher/CompressionPostprocessor.py
filecrusher/__init__.py
filecrusher/__main__.py
filecrusher/advpng_compressor.py
filecrusher/batch_processor.py
filecrusher/config.py
filecrusher/cpdfsqueeze_compressor.py
filecrusher/file_operations.py
filecrusher/pdf_compressor.py
filecrusher/pipeline_processor.py
filecrusher/png_compressor.py
filecrusher/pngcrush_compressor.py
filecrusher/pngquant_compressor.py
filecrusher/processor.py
filecrusher/compressor_lib/advpng/LICENCE.txt
filecrusher/compressor_lib/advpng/advpng.exe
filecrusher/compressor_lib/cpdfsqueeze/LICENCE.txt
filecrusher/compressor_lib/cpdfsqueeze/cpdfsqueeze.exe
filecrusher/compressor_lib/pngcrush/LICENCE.txt
filecrusher/compressor_lib/pngcrush/pngcrush.exe
filecrusher/compressor_lib/pngquant/LICENCE.txt
filecrusher/compressor_lib/pngquant/pngquant.exe
filecrusher/converter/__init__.py
filecrusher/converter/image_to_pdf_converter.py
filecrusher/converter/pdf_merger.py
filecrusher/converter/pdf_to_image_converter.py
filecrusher-0.2.5.dist-info/METADATA
filecrusher-0.2.5.dist-info/WHEEL
filecrusher-0.2.5.dist-info/top_level.txt
filecrusher-0.2.5.dist-info/RECORD
