Metadata-Version: 2.1
Name: filecrusher
Version: 0.2.5
Summary: Compresses PDFs with PNG compression.
Home-page: https://github.com/pilip-d/FileCrusher.git
Author: Philip Dell
Project-URL: Bug Reports, https://github.com/pIlIp-d/FileCrusher/issues
Project-URL: Source, https://github.com/pilip-d/FileCrusher.git
Keywords: compression pdf png GoodNotes file crusher crunch compress size limit
Classifier: Development Status :: 4 - Beta
Classifier: Intended Audience :: Developers
Classifier: License :: OSI Approved :: MIT License
Classifier: Natural Language :: English
Classifier: Programming Language :: Python
Classifier: Topic :: Utilities
Classifier: Topic :: File Formats
Requires-Python: <4,>=3.6
Requires-Dist: img2pdf>=0.1.4
Requires-Dist: pillow>=10.2.0
Requires-Dist: PyMuPDF>=1.22.0
Requires-Dist: pytesseract>=0.3.0
